granitepy/__init__.py
granitepy/client.py
granitepy/events.py
granitepy/exceptions.py
granitepy/filters.py
granitepy/node.py
granitepy/objects.py
granitepy/player.py
granitepy-0.4.2.dist-info/LICENSE
granitepy-0.4.2.dist-info/METADATA
granitepy-0.4.2.dist-info/WHEEL
granitepy-0.4.2.dist-info/top_level.txt
granitepy-0.4.2.dist-info/RECORD
