Metadata-Version: 2.1
Name: granitepy
Version: 0.4.2
Summary: A python client for the audio provider Andesite for use with discord.py.
Home-page: https://github.com/iDevision/granitepy
Author: MrRandom#9258 and twitch 🔋#7443
License: MIT
Keywords: andesite,granitepy,discord.py
Platform: UNKNOWN
Classifier: Framework :: AsyncIO
Classifier: Operating System :: OS Independent
Classifier: Natural Language :: English
Classifier: Intended Audience :: Developers
Classifier: Programming Language :: Python :: 3 :: Only
Classifier: Programming Language :: Python :: 3.6
Classifier: Programming Language :: Python :: 3.7
Classifier: Programming Language :: Python :: 3.8
Classifier: Topic :: Software Development :: Libraries :: Python Modules
Classifier: Topic :: Software Development :: Libraries
Classifier: Topic :: Internet
Requires-Python: >=3.6
Requires-Dist: discord.py (>=1.2.5)
